wagtailiconify/__init__.py
wagtailiconify/apps.py
wagtailiconify/blocks.py
wagtailiconify/choices/__init__.py
wagtailiconify/choices/fontawesome.py
wagtailiconify/develop/__init__.py
wagtailiconify/develop/scripts/__init__.py
wagtailiconify/develop/scripts/fontawesome.py
wagtailiconify/static/wagtailiconify/css/1551f4f60c37af51121f.woff2
wagtailiconify/static/wagtailiconify/css/2285773e6b4b172f07d9.woff
wagtailiconify/static/wagtailiconify/css/23f19bb08961f37aaf69.eot
wagtailiconify/static/wagtailiconify/css/2f517e09eb2ca6650ff5.svg
wagtailiconify/static/wagtailiconify/css/4689f52cc96215721344.svg
wagtailiconify/static/wagtailiconify/css/491974d108fe4002b2aa.ttf
wagtailiconify/static/wagtailiconify/css/527940b104eb2ea366c8.ttf
wagtailiconify/static/wagtailiconify/css/77206a6bb316fa0aded5.eot
wagtailiconify/static/wagtailiconify/css/7a3337626410ca2f4071.woff2
wagtailiconify/static/wagtailiconify/css/7a8b4f130182d19a2d7c.svg
wagtailiconify/static/wagtailiconify/css/9bbb245e67a133f6e486.eot
wagtailiconify/static/wagtailiconify/css/bb58e57c48a3e911f15f.woff
wagtailiconify/static/wagtailiconify/css/be9ee23c0c6390141475.ttf
wagtailiconify/static/wagtailiconify/css/d878b0a6a1144760244f.woff2
wagtailiconify/static/wagtailiconify/css/eeccf4f66002c6f2ba24.woff
wagtailiconify/static/wagtailiconify/css/wagtailiconify_fontawesome.js
wagtailiconify/static/wagtailiconify/css/wagtailiconify_fontawesome.min.css
wagtailiconify/templates/wagtailiconify/icon_block.html
wagtailiconify/templatetags/__init__.py
wagtailiconify/templatetags/wagtailiconify.py
wagtailiconify-0.0.1.dist-info/LICENSE
wagtailiconify-0.0.1.dist-info/METADATA
wagtailiconify-0.0.1.dist-info/WHEEL
wagtailiconify-0.0.1.dist-info/top_level.txt
wagtailiconify-0.0.1.dist-info/RECORD
