Metadata-Version: 2.1
Name: wagtailiconify
Version: 0.0.1
Summary: A plugin for Wagtail CMS, icon blocks (fontawesome)
Home-page: https://github.com/Nefonfo/wagtailiconify
Author: Nefonfo
Author-email: victorarmenta30@gmail.com
License: MIT
Keywords: development,django,wagtail
Platform: UNKNOWN
Classifier: Environment :: Web Environment
Classifier: Framework :: Django
Classifier: Intended Audience :: Developers
Classifier: Operating System :: OS Independent
Classifier: Programming Language :: Python
Classifier: Programming Language :: Python :: 3
Classifier: Topic :: Internet :: WWW/HTTP
Classifier: Topic :: Internet :: WWW/HTTP :: Dynamic Content
Requires-Python: >=3.8
License-File: LICENSE
Requires-Dist: wagtail (>=2.15.0)
Requires-Dist: Django (>=3.2.0)
